detect_qt_binding.py
detect_qt_binding-0.1.0a0.dist-info/licenses/LICENSE
detect_qt_binding-0.1.0a0.dist-info/METADATA
detect_qt_binding-0.1.0a0.dist-info/WHEEL
detect_qt_binding-0.1.0a0.dist-info/top_level.txt
detect_qt_binding-0.1.0a0.dist-info/RECORD
