Metadata-Version: 2.4
Name: detect-qt-binding
Version: 0.1.0a0
Summary: A lightweight utility to automatically detect which Qt Python binding is available in your environment.
Author-email: Jifeng Wu <jifengwu2k@gmail.com>
License-Expression: MIT
Project-URL: Homepage, https://github.com/jifengwu2k/detect-qt-binding
Project-URL: Bug Tracker, https://github.com/jifengwu2k/detect-qt-binding/issues
Classifier: Programming Language :: Python :: 2
Classifier: Programming Language :: Python :: 3
Classifier: Operating System :: OS Independent
Requires-Python: >=2
License-File: LICENSE
Requires-Dist: enum34; python_version < "3.4"
Requires-Dist: typing; python_version < "3.5"
Dynamic: license-file
